obs_controller/__init__.py
obs_controller/__main__.py
obs_controller/client.py
obs_controller/config.py
obs_controller/server.py
obs_controller/tools/__init__.py
obs_controller/tools/filters.py
obs_controller/tools/general.py
obs_controller/tools/inputs.py
obs_controller/tools/media.py
obs_controller/tools/outputs.py
obs_controller/tools/recording.py
obs_controller/tools/scene_items.py
obs_controller/tools/scenes.py
obs_controller/tools/sources.py
obs_controller/tools/streaming.py
obs_controller/tools/transitions.py
obs_controller/tools/ui.py
obs_controller-0.1.1.dist-info/METADATA
obs_controller-0.1.1.dist-info/WHEEL
obs_controller-0.1.1.dist-info/entry_points.txt
obs_controller-0.1.1.dist-info/licenses/LICENSE
obs_controller-0.1.1.dist-info/RECORD
