Metadata-Version: 2.4
Name: obs-controller
Version: 0.1.1
Summary: MCP server for controlling OBS Studio via WebSocket API
License-Expression: MIT
License-File: LICENSE
Keywords: obs,obs-studio,mcp,websocket,streaming,automation,claude
Author: ldraney
Requires-Python: >=3.10,<4.0
Classifier: Development Status :: 4 - Beta
Classifier: Intended Audience :: Developers
Classifier: Operating System :: OS Independent
Classifier: Programming Language :: Python :: 3
Classifier: Programming Language :: Python :: 3.10
Classifier: Programming Language :: Python :: 3.11
Classifier: Programming Language :: Python :: 3.12
Classifier: Topic :: Multimedia :: Video
Classifier: Topic :: System :: Networking
Requires-Dist: fastmcp (>=2.0.0)
Requires-Dist: obsws-python-mcp (>=1.8.1)
Requires-Dist: pydantic (>=2.0)
Requires-Dist: pydantic-settings (>=2.0)
Requires-Dist: python-dotenv (>=1.0.0)
Project-URL: Bug Tracker, https://github.com/ldraney/obs-controller/issues
Project-URL: Homepage, https://github.com/ldraney/obs-controller
Project-URL: Repository, https://github.com/ldraney/obs-controller
